odoo8_addon_res_currency_print_on_check-8.0.1.0.0.99.dev5-py2.7-nspkg.pth
odoo8_addon_res_currency_print_on_check-8.0.1.0.0.99.dev5.dist-info/METADATA
odoo8_addon_res_currency_print_on_check-8.0.1.0.0.99.dev5.dist-info/RECORD
odoo8_addon_res_currency_print_on_check-8.0.1.0.0.99.dev5.dist-info/WHEEL
odoo8_addon_res_currency_print_on_check-8.0.1.0.0.99.dev5.dist-info/namespace_packages.txt
odoo8_addon_res_currency_print_on_check-8.0.1.0.0.99.dev5.dist-info/top_level.txt
odoo_addons/res_currency_print_on_check/__init__.py
odoo_addons/res_currency_print_on_check/__openerp__.py
odoo_addons/res_currency_print_on_check/currency.py
odoo_addons/res_currency_print_on_check/currency_data.xml
odoo_addons/res_currency_print_on_check/currency_view.xml
odoo_addons/res_currency_print_on_check/i18n/fr.po
odoo_addons/res_currency_print_on_check/i18n/fr_CA.po
odoo_addons/res_currency_print_on_check/i18n/nb_NO.po
odoo_addons/res_currency_print_on_check/i18n/res_currency_print_on_check.pot
odoo_addons/res_currency_print_on_check/i18n/sl.po
odoo_addons/res_currency_print_on_check/static/description/icon.png
